{
  "wall_time_s": 1.345060082996497,
  "total_query_time_s": 0.7935771670599934,
  "total_advisor_time_s": 0.5473944169061724,
  "num_queries": 120,
  "errors": 0,
  "qps": 151.21402805044184,
  "wall_qps": 89.21534548305567,
  "advisor_calls": 7,
  "trigger_rate": 0.2916666666666667,
  "trigger_precision": 0.42857142857142855,
  "transitions_hit": 3,
  "transitions_total": 3,
  "latency_p50_ms": 0.3030840016435832,
  "latency_p95_ms": 48.66137498174794,
  "latency_p99_ms": 68.653833004646,
  "latency_mean_skip_ms": 5.022892741459039,
  "latency_mean_trigger_ms": 10.465497743072254,
  "per_window": [
    {
      "window_idx": 0,
      "phase": "ReadOnly",
      "hsm_score": 1.0,
      "triggered": 0,
      "is_true_trans": 0,
      "query_time_s": 0.0024781670072115958,
      "advisor_wall_s": 0.0,
      "n_ddl": 0,
      "dropped": 0,
      "created": 0,
      "errors": 0,
      "latencies_ms": [
        0.607,
        0.456,
        0.464,
        0.484,
        0.452
      ]
    },
    {
      "window_idx": 1,
      "phase": "ReadOnly",
      "hsm_score": 1.0,
      "triggered": 0,
      "is_true_trans": 0,
      "query_time_s": 0.0021539579902309924,
      "advisor_wall_s": 0.0,
      "n_ddl": 0,
      "dropped": 0,
      "created": 0,
      "errors": 0,
      "latencies_ms": [
        0.357,
        0.405,
        0.591,
        0.429,
        0.356
      ]
    },
    {
      "window_idx": 2,
      "phase": "ReadOnly",
      "hsm_score": 1.0,
      "triggered": 0,
      "is_true_trans": 0,
      "query_time_s": 0.0023186250182334334,
      "advisor_wall_s": 0.0,
      "n_ddl": 0,
      "dropped": 0,
      "created": 0,
      "errors": 0,
      "latencies_ms": [
        0.407,
        0.473,
        0.354,
        0.442,
        0.616
      ]
    },
    {
      "window_idx": 3,
      "phase": "ReadOnly",
      "hsm_score": 1.0,
      "triggered": 1,
      "is_true_trans": 0,
      "query_time_s": 0.00261875000433065,
      "advisor_wall_s": 0.019661250989884138,
      "n_ddl": 0,
      "dropped": 0,
      "created": 0,
      "errors": 0,
      "latencies_ms": [
        0.562,
        0.547,
        0.403,
        0.357,
        0.724
      ]
    },
    {
      "window_idx": 4,
      "phase": "ReadOnly",
      "hsm_score": 1.0,
      "triggered": 0,
      "is_true_trans": 0,
      "query_time_s": 0.0013487090182024986,
      "advisor_wall_s": 0.0,
      "n_ddl": 0,
      "dropped": 0,
      "created": 0,
      "errors": 0,
      "latencies_ms": [
        0.275,
        0.335,
        0.238,
        0.239,
        0.254
      ]
    },
    {
      "window_idx": 5,
      "phase": "ReadOnly",
      "hsm_score": 1.0,
      "triggered": 0,
      "is_true_trans": 0,
      "query_time_s": 0.0013271250063553452,
      "advisor_wall_s": 0.0,
      "n_ddl": 0,
      "dropped": 0,
      "created": 0,
      "errors": 0,
      "latencies_ms": [
        0.27,
        0.241,
        0.276,
        0.251,
        0.282
      ]
    },
    {
      "window_idx": 6,
      "phase": "WriteHeavy",
      "hsm_score": 1.0,
      "triggered": 1,
      "is_true_trans": 1,
      "query_time_s": 0.0021097080025356263,
      "advisor_wall_s": 0.009453166014282033,
      "n_ddl": 0,
      "dropped": 0,
      "created": 0,
      "errors": 0,
      "latencies_ms": [
        0.649,
        0.449,
        0.363,
        0.322,
        0.32
      ]
    },
    {
      "window_idx": 7,
      "phase": "WriteHeavy",
      "hsm_score": 1.0,
      "triggered": 0,
      "is_true_trans": 0,
      "query_time_s": 0.0013635840150527656,
      "advisor_wall_s": 0.0,
      "n_ddl": 0,
      "dropped": 0,
      "created": 0,
      "errors": 0,
      "latencies_ms": [
        0.327,
        0.284,
        0.201,
        0.281,
        0.267
      ]
    },
    {
      "window_idx": 8,
      "phase": "WriteHeavy",
      "hsm_score": 1.0,
      "triggered": 0,
      "is_true_trans": 0,
      "query_time_s": 0.0013944589882157743,
      "advisor_wall_s": 0.0,
      "n_ddl": 0,
      "dropped": 0,
      "created": 0,
      "errors": 0,
      "latencies_ms": [
        0.303,
        0.27,
        0.265,
        0.268,
        0.281
      ]
    },
    {
      "window_idx": 9,
      "phase": "WriteHeavy",
      "hsm_score": 1.0,
      "triggered": 1,
      "is_true_trans": 0,
      "query_time_s": 0.0013598339864984155,
      "advisor_wall_s": 0.008470582979498431,
      "n_ddl": 0,
      "dropped": 0,
      "created": 0,
      "errors": 0,
      "latencies_ms": [
        0.269,
        0.25,
        0.266,
        0.282,
        0.289
      ]
    },
    {
      "window_idx": 10,
      "phase": "WriteHeavy",
      "hsm_score": 1.0,
      "triggered": 0,
      "is_true_trans": 0,
      "query_time_s": 0.0012948749936185777,
      "advisor_wall_s": 0.0,
      "n_ddl": 0,
      "dropped": 0,
      "created": 0,
      "errors": 0,
      "latencies_ms": [
        0.233,
        0.318,
        0.221,
        0.251,
        0.267
      ]
    },
    {
      "window_idx": 11,
      "phase": "WriteHeavy",
      "hsm_score": 1.0,
      "triggered": 0,
      "is_true_trans": 0,
      "query_time_s": 0.0012409159971866757,
      "advisor_wall_s": 0.0,
      "n_ddl": 0,
      "dropped": 0,
      "created": 0,
      "errors": 0,
      "latencies_ms": [
        0.257,
        0.262,
        0.304,
        0.246,
        0.169
      ]
    },
    {
      "window_idx": 12,
      "phase": "Mixed",
      "hsm_score": 1.0,
      "triggered": 1,
      "is_true_trans": 1,
      "query_time_s": 0.0009240420185960829,
      "advisor_wall_s": 0.008087749971309677,
      "n_ddl": 0,
      "dropped": 0,
      "created": 0,
      "errors": 0,
      "latencies_ms": [
        0.169,
        0.271,
        0.169,
        0.163,
        0.148
      ]
    },
    {
      "window_idx": 13,
      "phase": "Mixed",
      "hsm_score": 1.0,
      "triggered": 0,
      "is_true_trans": 0,
      "query_time_s": 0.0011547500034794211,
      "advisor_wall_s": 0.0,
      "n_ddl": 0,
      "dropped": 0,
      "created": 0,
      "errors": 0,
      "latencies_ms": [
        0.267,
        0.253,
        0.165,
        0.222,
        0.244
      ]
    },
    {
      "window_idx": 14,
      "phase": "Mixed",
      "hsm_score": 1.0,
      "triggered": 0,
      "is_true_trans": 0,
      "query_time_s": 0.0010795829875860363,
      "advisor_wall_s": 0.0,
      "n_ddl": 0,
      "dropped": 0,
      "created": 0,
      "errors": 0,
      "latencies_ms": [
        0.262,
        0.16,
        0.162,
        0.253,
        0.239
      ]
    },
    {
      "window_idx": 15,
      "phase": "Mixed",
      "hsm_score": 1.0,
      "triggered": 1,
      "is_true_trans": 0,
      "query_time_s": 0.0008742079953663051,
      "advisor_wall_s": 0.007313624984817579,
      "n_ddl": 0,
      "dropped": 0,
      "created": 0,
      "errors": 0,
      "latencies_ms": [
        0.165,
        0.241,
        0.157,
        0.154,
        0.153
      ]
    },
    {
      "window_idx": 16,
      "phase": "Mixed",
      "hsm_score": 1.0,
      "triggered": 0,
      "is_true_trans": 0,
      "query_time_s": 0.0008863330003805459,
      "advisor_wall_s": 0.0,
      "n_ddl": 0,
      "dropped": 0,
      "created": 0,
      "errors": 0,
      "latencies_ms": [
        0.222,
        0.134,
        0.211,
        0.192,
        0.12
      ]
    },
    {
      "window_idx": 17,
      "phase": "Mixed",
      "hsm_score": 1.0,
      "triggered": 0,
      "is_true_trans": 0,
      "query_time_s": 0.0009013329981826246,
      "advisor_wall_s": 0.0,
      "n_ddl": 0,
      "dropped": 0,
      "created": 0,
      "errors": 0,
      "latencies_ms": [
        0.22,
        0.204,
        0.195,
        0.137,
        0.138
      ]
    },
    {
      "window_idx": 18,
      "phase": "BulkRead",
      "hsm_score": 1.0,
      "triggered": 1,
      "is_true_trans": 1,
      "query_time_s": 0.19632454199017957,
      "advisor_wall_s": 0.48316720899310894,
      "n_ddl": 3,
      "dropped": 0,
      "created": 3,
      "errors": 0,
      "latencies_ms": [
        55.305,
        48.661,
        31.494,
        29.182,
        31.656
      ]
    },
    {
      "window_idx": 19,
      "phase": "BulkRead",
      "hsm_score": 1.0,
      "triggered": 0,
      "is_true_trans": 0,
      "query_time_s": 0.04521970800124109,
      "advisor_wall_s": 0.0,
      "n_ddl": 0,
      "dropped": 0,
      "created": 0,
      "errors": 0,
      "latencies_ms": [
        6.79,
        12.066,
        12.946,
        7.577,
        5.808
      ]
    },
    {
      "window_idx": 20,
      "phase": "BulkRead",
      "hsm_score": 1.0,
      "triggered": 0,
      "is_true_trans": 0,
      "query_time_s": 0.03961237502517179,
      "advisor_wall_s": 0.0,
      "n_ddl": 0,
      "dropped": 0,
      "created": 0,
      "errors": 0,
      "latencies_ms": [
        7.063,
        7.099,
        6.245,
        7.16,
        12.01
      ]
    },
    {
      "window_idx": 21,
      "phase": "BulkRead",
      "hsm_score": 1.0,
      "triggered": 1,
      "is_true_trans": 0,
      "query_time_s": 0.1621814579993952,
      "advisor_wall_s": 0.011240832973271608,
      "n_ddl": 0,
      "dropped": 3,
      "created": 0,
      "errors": 0,
      "latencies_ms": [
        6.772,
        68.414,
        6.456,
        68.654,
        11.858
      ]
    },
    {
      "window_idx": 22,
      "phase": "BulkRead",
      "hsm_score": 1.0,
      "triggered": 0,
      "is_true_trans": 0,
      "query_time_s": 0.16451929201139137,
      "advisor_wall_s": 0.0,
      "n_ddl": 0,
      "dropped": 0,
      "created": 0,
      "errors": 0,
      "latencies_ms": [
        69.511,
        6.724,
        27.295,
        32.112,
        28.848
      ]
    },
    {
      "window_idx": 23,
      "phase": "BulkRead",
      "hsm_score": 1.0,
      "triggered": 0,
      "is_true_trans": 0,
      "query_time_s": 0.15889083300135098,
      "advisor_wall_s": 0.0,
      "n_ddl": 0,
      "dropped": 0,
      "created": 0,
      "errors": 0,
      "latencies_ms": [
        32.074,
        49.151,
        6.682,
        60.009,
        10.943
      ]
    }
  ]
}